setup.py
Serializer_Lasevich.egg-info/PKG-INFO
Serializer_Lasevich.egg-info/SOURCES.txt
Serializer_Lasevich.egg-info/dependency_links.txt
Serializer_Lasevich.egg-info/top_level.txt
serializers/__init__.py
serializers/factory_serializer.py
serializers/dict_serilizer/__init__.py
serializers/dict_serilizer/functions.py
serializers/json/__init__.py
serializers/json/json.py
serializers/json/parse_json.py
serializers/xml/__init__.py
serializers/xml/xml.py
serializers/xml/xml_parser.py